checkpoint_client/__init__.py
checkpoint_client/utils.py
checkpoint_client/api_client/__init__.py
checkpoint_client-0.0.1.dist-info/LICENSE
checkpoint_client-0.0.1.dist-info/METADATA
checkpoint_client-0.0.1.dist-info/WHEEL
checkpoint_client-0.0.1.dist-info/top_level.txt
checkpoint_client-0.0.1.dist-info/RECORD
